pasero.py
pasero-0.0.1.dist-info/METADATA
pasero-0.0.1.dist-info/WHEEL
pasero-0.0.1.dist-info/entry_points.txt
pasero-0.0.1.dist-info/top_level.txt
pasero-0.0.1.dist-info/RECORD
