Metadata-Version: 2.1
Name: pasero
Version: 0.0.1
Summary: pasero for detecting pathogen-serotype outbreaks
Home-page: https://github.com/y-takefuji/pasero
Author: yoshiyasu takefuji
Author-email: takefuji@keio.jp
Project-URL: Bug Tracker, https://github.com/y-takefuji/pasero
Classifier: Programming Language :: Python :: 3
Classifier: License :: OSI Approved :: MIT License
Classifier: Operating System :: OS Independent
Requires-Python: >=3.8
